README.rst
ng.py
setup.py
ng.egg-info/PKG-INFO
ng.egg-info/SOURCES.txt
ng.egg-info/dependency_links.txt
ng.egg-info/entry_points.txt
ng.egg-info/not-zip-safe
ng.egg-info/requires.txt
ng.egg-info/top_level.txt