Metadata-Version: 1.1
Name: ng
Version: 1.2.0
Summary: Get password of the wifi you're connected, and your current ip address.
Home-page: https://github.com/cls1991/ng
Author: cls1991
Author-email: tzk19910406@hotmail.com
License: Apache License 2.0
Keywords: wifi,password,ip
Platform: any
Classifier: Development Status :: 4 - Beta
Classifier: Intended Audience :: Developers
Classifier: Natural Language :: English
Classifier: License :: OSI Approved :: Apache Software License
Classifier: Programming Language :: Python
Classifier: Programming Language :: Python :: 2.7
Classifier: Programming Language :: Python :: 3
Classifier: Programming Language :: Python :: 3.3
Classifier: Programming Language :: Python :: 3.4
Classifier: Programming Language :: Python :: 3.5
Classifier: Programming Language :: Python :: 3.6
Classifier: Programming Language :: Python :: Implementation :: CPython
Classifier: Programming Language :: Python :: Implementation :: PyPy
Classifier: Operating System :: OS Independent
